paypack/__init__.py
paypack/client.py
paypack/config.py
paypack/events.py
paypack/http_client.py
paypack/merchant.py
paypack/oauth2.py
paypack/transactions.py
paypack_py-1.0.5.dist-info/LICENSE
paypack_py-1.0.5.dist-info/METADATA
paypack_py-1.0.5.dist-info/WHEEL
paypack_py-1.0.5.dist-info/top_level.txt
paypack_py-1.0.5.dist-info/RECORD
