Metadata-Version: 2.1
Name: paypack-py
Version: 1.0.5
Summary: Python and Django SDK for Paypack API Payment Gateway
Home-page: UNKNOWN
Author: QuarksGroup
Author-email: info@quarksgroup.rw
License: MIT
Keywords: paypack,paypack-py-rwanda,payment-py,payments,paypack-py,paypack-py-sdk,paypack-py-sdk-django,paypack-py-sdk-flask,paypack-py-sdk-pyramid,paypack-py-sdk-tornado,paypack-py-sdk-web,paypack-py-sdk-web-django,paypack-py-sdk-web-flask,paypack-py-sdk-web-pyramid,paypack-py-sdk-web-tornado
Platform: UNKNOWN
Classifier: Development Status :: 5 - Production/Stable
Classifier: License :: OSI Approved :: MIT License
Classifier: Programming Language :: Python :: 3
Classifier: Programming Language :: Python :: 3.6
Classifier: Programming Language :: Python :: 3.7
Classifier: Programming Language :: Python :: 3.8
Requires-Dist: requests (~=2.26.0)
